{"mean":{"confidence_interval":{"confidence_level":0.95,"lower_bound":137785844.1143393,"upper_bound":141224028.1844137},"point_estimate":139370046.75440472,"standard_error":885535.3138473998},"median":{"confidence_interval":{"confidence_level":0.95,"lower_bound":137047510.5,"upper_bound":141265589.2857143},"point_estimate":138368277.75,"standard_error":1104252.2217948935},"median_abs_dev":{"confidence_interval":{"confidence_level":0.95,"lower_bound":207198.53542149067,"upper_bound":4987673.963701103},"point_estimate":2729384.1436937526,"standard_error":1085014.8188687835},"slope":{"confidence_interval":{"confidence_level":0.95,"lower_bound":138770150.28413284,"upper_bound":142868960.40898344},"point_estimate":141050420.71688312,"standard_error":1024669.6135026127},"std_dev":{"confidence_interval":{"confidence_level":0.95,"lower_bound":1378826.369109502,"upper_bound":3909189.312776998},"point_estimate":2938357.0215053894,"standard_error":699795.4001164233}}