{"mean":{"confidence_interval":{"confidence_level":0.95,"lower_bound":27984515.239603173,"upper_bound":28205387.93646259},"point_estimate":28100235.436797053,"standard_error":56696.224017424756},"median":{"confidence_interval":{"confidence_level":0.95,"lower_bound":27939686.298611112,"upper_bound":28238501.476190478},"point_estimate":28152934.5,"standard_error":82059.17059835585},"median_abs_dev":{"confidence_interval":{"confidence_level":0.95,"lower_bound":28435.14798088758,"upper_bound":318629.37715569674},"point_estimate":165939.90792064447,"standard_error":75769.5713971847},"slope":{"confidence_interval":{"confidence_level":0.95,"lower_bound":27863863.011494253,"upper_bound":28170225.753447324},"point_estimate":27987006.600742117,"standard_error":78402.56671648227},"std_dev":{"confidence_interval":{"confidence_level":0.95,"lower_bound":96715.91175540787,"upper_bound":234575.25886422698},"point_estimate":188921.2700863857,"standard_error":34702.60082435105}}